packtools/__init__.py
packtools/domain.py
packtools/exceptions.py
packtools/htmlgenerator.py
packtools/package_optimiser.py
packtools/style_errors.py
packtools/stylechecker.py
packtools/utils.py
packtools/version.py
packtools/catalogs/__init__.py
packtools/catalogs/checks.py
packtools/catalogs/common.sch
packtools/catalogs/iso3166-codes.json
packtools/catalogs/scielo-br.sch
packtools/catalogs/scielo-publishing-schema.xml
packtools/catalogs/scielo-style-1.1.sch
packtools/catalogs/scielo-style-1.10.sch
packtools/catalogs/scielo-style-1.2.sch
packtools/catalogs/scielo-style-1.3.sch
packtools/catalogs/scielo-style-1.4.sch
packtools/catalogs/scielo-style-1.5.sch
packtools/catalogs/scielo-style-1.6.sch
packtools/catalogs/scielo-style-1.7.sch
packtools/catalogs/scielo-style-1.8.sch
packtools/catalogs/scielo-style-1.9.sch
packtools/catalogs/htmlgenerator/root-html-1.2.xslt
packtools/catalogs/htmlgenerator/root-html-2.0.xslt
packtools/catalogs/htmlgenerator/static/scielo-article-standalone-min.js
packtools/catalogs/htmlgenerator/static/scielo-article-standalone.css
packtools/catalogs/htmlgenerator/static/scielo-bundle-print.css
packtools/catalogs/htmlgenerator/v1.2/article.xsl
packtools/catalogs/htmlgenerator/v2.0/article-meta-abstract.xsl
packtools/catalogs/htmlgenerator/v2.0/article-meta-contrib.xsl
packtools/catalogs/htmlgenerator/v2.0/article-meta-permissions.xsl
packtools/catalogs/htmlgenerator/v2.0/article-meta-product.xsl
packtools/catalogs/htmlgenerator/v2.0/article-meta-related-article.xsl
packtools/catalogs/htmlgenerator/v2.0/article-meta.xsl
packtools/catalogs/htmlgenerator/v2.0/article-text-alternatives.xsl
packtools/catalogs/htmlgenerator/v2.0/article-text-back.xsl
packtools/catalogs/htmlgenerator/v2.0/article-text-bio.xsl
packtools/catalogs/htmlgenerator/v2.0/article-text-boxed-text.xsl
packtools/catalogs/htmlgenerator/v2.0/article-text-def-list.xsl
packtools/catalogs/htmlgenerator/v2.0/article-text-fig.xsl
packtools-2.6.4.dist-info/LICENSE
packtools-2.6.4.dist-info/METADATA
packtools-2.6.4.dist-info/WHEEL
packtools-2.6.4.dist-info/entry_points.txt
packtools-2.6.4.dist-info/top_level.txt
packtools-2.6.4.dist-info/RECORD
