Metadata-Version: 2.1
Name: packtools
Version: 2.6.4
Summary: Handle SPS packages like a breeze.
Home-page: http://docs.scielo.org
Author: SciELO
Author-email: scielo-dev@googlegroups.com
Maintainer: Gustavo Fonseca
Maintainer-email: gustavo.fonseca@scielo.org
License: BSD License
Platform: UNKNOWN
Classifier: Development Status :: 4 - Beta
Classifier: Intended Audience :: Developers
Classifier: Programming Language :: Python :: 2.7
Classifier: Programming Language :: Python :: 3.5
Classifier: Programming Language :: Python :: 3.6
Classifier: Programming Language :: Python :: 3.7
Classifier: Topic :: Software Development :: Libraries :: Python Modules
Requires-Dist: lxml (>=4.2.0)
Requires-Dist: picles.plumber (>=0.11)
Requires-Dist: Pillow (~=6.2)
Requires-Dist: pathlib (>=1.0.1) ; python_version<"3.4"
Provides-Extra: webapp
Requires-Dist: Flask ; extra == 'webapp'
Requires-Dist: Flask-BabelEx ; extra == 'webapp'
Requires-Dist: Flask-WTF ; extra == 'webapp'
Requires-Dist: Werkzeug (==0.16.1) ; extra == 'webapp'
